qt_api/__init__.py
qtframelesswindow/__init__.py
qtframelesswindow/buttons.py
qtframelesswindow/manager.py
qtframelesswindow/resource.py
qtframelesswindow/window.py
QtPy_Frameless_Window-0.1.2.dist-info/WHEEL
QtPy_Frameless_Window-0.1.2.dist-info/METADATA
QtPy_Frameless_Window-0.1.2.dist-info/licenses/LICENSE
QtPy_Frameless_Window-0.1.2.dist-info/RECORD
