Metadata-Version: 2.1
Name: QtPy-Frameless-Window
Version: 0.1.2
Summary: A cross-platform frameless window based on QtPy.
License: GPLv3
Keywords: pyqt frameless
Author-email: TaoChenyue <3038816978@qq.com>
Requires-Python: >=3.7,<3.10
Classifier: License :: OSI Approved :: GNU General Public License v3 (GPLv3)
Classifier: Operating System :: OS Independent
Classifier: Programming Language :: Python :: 3
Requires-Dist: qtpy
Provides-Extra: pyqt
Requires-Dist: pyside2; extra == "pyqt"
Requires-Dist: pyside6; extra == "pyqt"
Requires-Dist: pyqt5; extra == "pyqt"
Requires-Dist: pyqt6; extra == "pyqt"
Project-URL: Homepage, https://github.com/TaoChenyue/QtPy-Frameless-Window.git
